odoo/addons/l10n_ch_cooperator/README.rst
odoo/addons/l10n_ch_cooperator/__init__.py
odoo/addons/l10n_ch_cooperator/__manifest__.py
odoo/addons/l10n_ch_cooperator/i18n/it.po
odoo/addons/l10n_ch_cooperator/i18n/l10n_ch_cooperator.pot
odoo/addons/l10n_ch_cooperator/models/__init__.py
odoo/addons/l10n_ch_cooperator/models/res_partner.py
odoo/addons/l10n_ch_cooperator/models/subscription_request.py
odoo/addons/l10n_ch_cooperator/readme/CONTRIBUTORS.rst
odoo/addons/l10n_ch_cooperator/readme/DESCRIPTION.rst
odoo/addons/l10n_ch_cooperator/static/description/icon.png
odoo/addons/l10n_ch_cooperator/static/description/index.html
odoo/addons/l10n_ch_cooperator/views/subscription_template.xml
odoo_addon_l10n_ch_cooperator-16.0.1.0.0.8.dist-info/METADATA
odoo_addon_l10n_ch_cooperator-16.0.1.0.0.8.dist-info/WHEEL
odoo_addon_l10n_ch_cooperator-16.0.1.0.0.8.dist-info/top_level.txt
odoo_addon_l10n_ch_cooperator-16.0.1.0.0.8.dist-info/RECORD
